{"is_source_file": true, "format": "JavaScript (React JSX)", "description": "This source file defines a React functional component named TopNav, which provides a top navigation bar with buttons for adding expenses and viewing reports. The component uses react-router-dom's useNavigate hook to handle navigation actions.", "external_files": ["react", "react-router-dom"], "external_methods": ["useNavigate"], "published": [], "classes": [], "methods": [{"name": "TopNav()", "description": "React functional component rendering a top navigation bar with quick action buttons.", "scope": "", "scopeKind": ""}], "calls": ["useNavigate", "navigate('/transactions')", "navigate('/reports')"], "search-terms": ["TopNav", "React component", "navigation buttons", "react-router-dom", "useNavigate", "expense tracker header"], "state": 2, "file_id": 16, "knowledge_revision": 162, "git_revision": "8b368e628fd02ccfa52bfb480873ff8cf4ee785a", "revision_history": [{"37": ""}, {"162": "8b368e628fd02ccfa52bfb480873ff8cf4ee785a"}], "ctags": [{"_type": "tag", "name": "TopNav", "path": "/home/kavia/workspace/code-generation/smart-expense-tracker-4468-4477/expense_tracker_frontend/src/components/TopNav.jsx", "pattern": "/^export default function TopNav() {$/", "language": "JavaScript", "kind": "function", "signature": "()"}], "hash": "955314debaee73feeafc6474369c218c", "format-version": 4, "code-base-name": "expense_tracker_frontend", "filename": "expense_tracker_frontend/src/components/TopNav.jsx"}